mr_processing/__init__.py
mr_processing/processing/__init__.py
mr_processing/processing/combination.py
mr_processing/processing/grayScale.py
mr_processing/processing/transformation.py
mr_processing/utils/__init__.py
mr_processing/utils/io.py
mr_processing/utils/plot.py
mr_processing-0.1.8.dist-info/METADATA
mr_processing-0.1.8.dist-info/WHEEL
mr_processing-0.1.8.dist-info/top_level.txt
mr_processing-0.1.8.dist-info/RECORD
