Metadata-Version: 2.4
Name: mr-processing
Version: 0.1.8
Summary: Basic processing image package
Author: Mr Marius
Requires-Python: >=3.11
Requires-Dist: pillow
Requires-Dist: matplotlib
Requires-Dist: numpy
Requires-Dist: scikit-image>=0.16.1
